setup.py
tcopy/__init__.py
tcopy/tco.py
tcopy.egg-info/PKG-INFO
tcopy.egg-info/SOURCES.txt
tcopy.egg-info/dependency_links.txt
tcopy.egg-info/top_level.txt