Metadata-Version: 1.1
Name: tcopy
Version: 0.1.1
Summary: Basic tail call removal decorator
Home-page: https://github.com/Bogdanp/tcopy
Author: Bogdan Popa
Author-email: popa.bogdanp@gmail.com
License: UNKNOWN
Keywords: dangerous,optimization,useless
Platform: UNKNOWN
Classifier: Development Status :: 3 - Alpha
Classifier: Intended Audience :: Education
Classifier: License :: OSI Approved :: MIT License
Classifier: Topic :: Software Development :: Code Generators
Classifier: Topic :: Software Development :: Interpreters
